{
  "project_info": {
    "project_number": "315682846166",
    "project_id": "birthdayapp-a3688",
    "storage_bucket": "birthdayapp-a3688.appspot.com"
  },
  "client": [
    {
      "client_info": {
        "mobilesdk_app_id": "1:315682846166:android:81f7858e9879982956e077",
        "android_client_info": {
          "package_name": "com.birthdayapp"
        }
      },
      "oauth_client": [
        {
          "client_id": "315682846166-5p6c8llam7u08apfejhentlidpsdvmbe.apps.googleusercontent.com",
          "client_type": 3
        }
      ],
      "api_key": [
        {
          "current_key": "AIzaSyCVgaQoxbtMaOtzcU_os7egyvC35FVgks8"
        }
      ],
      "services": {
        "appinvite_service": {
          "other_platform_oauth_client": [
            {
              "client_id": "315682846166-5p6c8llam7u08apfejhentlidpsdvmbe.apps.googleusercontent.com",
              "client_type": 3
            }
          ]
        }
      }
    }
  ],
  "configuration_version": "1"
}